swutil/__init__.py
swutil/collections.py
swutil/config.py
swutil/decorators.py
swutil/files.py
swutil/future.py
swutil/hpc.py
swutil/logs.py
swutil/misc.py
swutil/np_tools.py
swutil/plots.py
swutil/stochastic_processes.py
swutil/sys_info.py
swutil/time.py
swutil/validation.py
swutil-1.4.4.dist-info/LICENSE
swutil-1.4.4.dist-info/METADATA
swutil-1.4.4.dist-info/WHEEL
swutil-1.4.4.dist-info/top_level.txt
swutil-1.4.4.dist-info/RECORD
