Metadata-Version: 2.1
Name: swutil
Version: 1.4.4
Summary: Provide common code for validation, multiprocessing, logging, decorator, configuration, plotting, etc.
Home-page: https://github.com/soerenwolfers/swutil
Author: Soeren Wolfers
Author-email: soeren.wolfers@gmail.com
License: UNKNOWN
Platform: UNKNOWN
Requires-Python: >=3.6
Requires-Dist: numpy
Requires-Dist: matplotlib
Requires-Dist: tikzplotlib
Requires-Dist: memory-profiler
Requires-Dist: pathos
Requires-Dist: dill
Requires-Dist: PyPDF2
